{
  "2": {
    "pick": "not_ok",
    "note": "",
    "time": "2026-06-17T07:13:34.333Z"
  },
  "5": {
    "pick": "ok",
    "note": "",
    "time": "2026-06-17T07:13:34.333Z"
  },
  "6": {
    "pick": "ok",
    "note": "",
    "time": "2026-06-17T07:13:34.333Z"
  },
  "9": {
    "pick": "not_ok",
    "note": "",
    "time": "2026-06-17T07:13:34.333Z"
  },
  "11": {
    "pick": "ok",
    "note": "",
    "time": "2026-06-17T07:13:34.333Z"
  },
  "13": {
    "pick": "ok",
    "note": "",
    "time": "2026-06-17T07:13:34.333Z"
  },
  "15": {
    "pick": "ok",
    "note": "",
    "time": "2026-06-17T07:13:34.333Z"
  },
  "24": {
    "pick": "ok",
    "note": "",
    "time": "2026-06-17T07:13:34.333Z"
  },
  "25": {
    "pick": "ok",
    "note": "",
    "time": "2026-06-17T07:13:34.333Z"
  },
  "27": {
    "pick": "not_ok",
    "note": "",
    "time": "2026-06-17T07:13:34.333Z"
  },
  "28": {
    "pick": "ok",
    "note": "",
    "time": "2026-06-17T07:13:34.333Z"
  },
  "30": {
    "pick": "not_ok",
    "note": "",
    "time": "2026-06-17T07:13:34.333Z"
  },
  "35": {
    "pick": "ok",
    "note": "",
    "time": "2026-06-17T07:13:34.333Z"
  },
  "46": {
    "pick": "ok",
    "note": "",
    "time": "2026-06-17T07:13:34.333Z"
  },
  "47": {
    "pick": "ok",
    "note": "",
    "time": "2026-06-17T07:13:34.333Z"
  },
  "48": {
    "pick": "not_ok",
    "note": "",
    "time": "2026-06-17T07:13:34.333Z"
  },
  "49": {
    "pick": "ok",
    "note": "",
    "time": "2026-06-17T07:13:34.333Z"
  },
  "50": {
    "pick": "ok",
    "note": "",
    "time": "2026-06-17T07:13:34.333Z"
  },
  "54": {
    "pick": "ok",
    "note": "",
    "time": "2026-06-17T07:13:34.333Z"
  },
  "55": {
    "pick": "ok",
    "note": "",
    "time": "2026-06-17T07:13:34.333Z"
  },
  "56": {
    "pick": "not_ok",
    "note": "不够美",
    "time": "2026-06-17T07:13:34.333Z"
  },
  "61": {
    "pick": "ok",
    "note": "",
    "time": "2026-06-17T07:13:34.333Z"
  },
  "62": {
    "pick": "ok",
    "note": "",
    "time": "2026-06-17T07:13:34.333Z"
  },
  "73": {
    "pick": "ok",
    "note": "",
    "time": "2026-06-17T07:13:34.333Z"
  }
}